torch_weightsonly/__init__.py
torch_weightsonly-1.0.1.dist-info/WHEEL
torch_weightsonly-1.0.1.dist-info/METADATA
torch_weightsonly-1.0.1.dist-info/RECORD
