Metadata-Version: 2.3
Name: torch_weightsonly
Version: 1.0.1
Summary: Stop Torch from moaning about weights, and load them safely
Author-email: Gareth Davidson <gaz@bitplane.net>
Requires-Dist: flake8 ; extra == "dev"
Requires-Dist: pre-commit ; extra == "dev"
Requires-Dist: pytest ; extra == "dev"
Requires-Dist: coverage ; extra == "dev"
Requires-Dist: pytest-cov ; extra == "dev"
Provides-Extra: dev
